unitycatalog_client_preview/__init__.py
unitycatalog_client_preview/api/__init__.py
unitycatalog_client_preview/api/catalogs_api.py
unitycatalog_client_preview/api/functions_api.py
unitycatalog_client_preview/api/grants_api.py
unitycatalog_client_preview/api/metastores_api.py
unitycatalog_client_preview/api/model_versions_api.py
unitycatalog_client_preview/api/registered_models_api.py
unitycatalog_client_preview/api/schemas_api.py
unitycatalog_client_preview/api/tables_api.py
unitycatalog_client_preview/api/temporary_credentials_api.py
unitycatalog_client_preview/api/volumes_api.py
unitycatalog_client_preview/api_client.py
unitycatalog_client_preview/api_response.py
unitycatalog_client_preview/configuration.py
unitycatalog_client_preview/exceptions.py
unitycatalog_client_preview/models/__init__.py
unitycatalog_client_preview/models/aws_credentials.py
unitycatalog_client_preview/models/azure_user_delegation_sas.py
unitycatalog_client_preview/models/catalog_info.py
unitycatalog_client_preview/models/column_info.py
unitycatalog_client_preview/models/column_type_name.py
unitycatalog_client_preview/models/create_catalog.py
unitycatalog_client_preview/models/create_function.py
unitycatalog_client_preview/models/create_function_request.py
unitycatalog_client_preview/models/create_model_version.py
unitycatalog_client_preview/models/create_registered_model.py
unitycatalog_client_preview/models/create_schema.py
unitycatalog_client_preview/models/create_table.py
unitycatalog_client_preview/models/create_volume_request_content.py
unitycatalog_client_preview/models/data_source_format.py
unitycatalog_client_preview/models/dependency.py
unitycatalog_client_preview/models/dependency_list.py
unitycatalog_client_preview/models/finalize_model_version.py
unitycatalog_client_preview/models/function_dependency.py
unitycatalog_client_preview/models/function_info.py
unitycatalog_client_preview/models/function_parameter_info.py
unitycatalog_client_preview/models/function_parameter_infos.py
unitycatalog_client_preview-1.0.1.dist-info/METADATA
unitycatalog_client_preview-1.0.1.dist-info/WHEEL
unitycatalog_client_preview-1.0.1.dist-info/RECORD
